consoly/__init__.py
consoly/color.py
consoly/consoly.py
consoly/formatter/__init__.py
consoly/formatter/fancyFormatter.py
consoly/formatter/formatter.py
consoly-0.0.1.dist-info/LICENSE.txt
consoly-0.0.1.dist-info/METADATA
consoly-0.0.1.dist-info/WHEEL
consoly-0.0.1.dist-info/top_level.txt
consoly-0.0.1.dist-info/RECORD
