Metadata-Version: 2.1
Name: consoly
Version: 0.0.1
Summary: elegant console logger for python
Home-page: https://github.com/OAlienO/consoly
Author: oalieno
Author-email: jeffrey6910@gmail.com
License: MIT
Keywords: color console terminal ansi text hues logging logger
Platform: UNKNOWN
Classifier: License :: OSI Approved :: MIT License
Classifier: Programming Language :: Python :: 3
Classifier: Programming Language :: Python :: 3.6
Classifier: Programming Language :: Python :: 3.7
Classifier: Programming Language :: Python :: 3.8
Requires-Python: >=3.6
